cap_from_youtube/__init__.py
cap_from_youtube/cap_from_youtube.py
cap_from_youtube-0.2.0.dist-info/LICENSE
cap_from_youtube-0.2.0.dist-info/METADATA
cap_from_youtube-0.2.0.dist-info/WHEEL
cap_from_youtube-0.2.0.dist-info/top_level.txt
cap_from_youtube-0.2.0.dist-info/RECORD
