Metadata-Version: 2.1
Name: cap_from_youtube
Version: 0.2.0
Summary: Get an OpenCV video capture from an YouTube video URL
Author: Ibai Gorordo
License: MIT
Project-URL: Homepage, https://github.com/ibaiGorordo/cap_from_youtube
License-File: LICENSE
Requires-Dist: yt-dlp
Requires-Dist: opencv-python
